README
setup.py
TracDjangoAuth.egg-info/PKG-INFO
TracDjangoAuth.egg-info/SOURCES.txt
TracDjangoAuth.egg-info/dependency_links.txt
TracDjangoAuth.egg-info/entry_points.txt
TracDjangoAuth.egg-info/requires.txt
TracDjangoAuth.egg-info/top_level.txt
tracdjangoauth/__init__.py
tracdjangoauth/auth_django.py