Metadata-Version: 1.1
Name: TracDjangoAuth
Version: 0.2
Summary: Trac Authentication against Django's userdb
Home-page: https://github.com/ypcs/TracDjangoAuth
Author: Ville Korhonen
Author-email: ville@xd.fi
License: UNKNOWN
Download-URL: https://github.com/ypcs/TracDjangoAuth/tarball/master
Keywords: AccountManager,acct_mgr,authentication,Django,Trac
Platform: UNKNOWN
Classifier: Development Status :: 4 - Beta
Classifier: Environment :: Other Environment
Classifier: Framework :: Django
Classifier: Framework :: Trac
Classifier: Intended Audience :: Developers
Classifier: Intended Audience :: System Administrators
Classifier: License :: OSI Approved :: GNU General Public License (GPL)
Classifier: Operating System :: OS Independent
Classifier: Programming Language :: Python
Classifier: Topic :: System :: Systems Administration :: Authentication/Directory
